a2a_agent_mcpserver_generator/__init__.py
a2a_agent_mcpserver_generator/app.py
a2a_agent_mcpserver_generator/config_generator.py
a2a_agent_mcpserver_generator/dockerfile_generator.py
a2a_agent_mcpserver_generator/server_generator.py
a2a_agent_mcpserver_generator/types.py
a2a_agent_mcpserver_generator/utils.py
a2a_agent_mcpserver_generator-0.1.2.dist-info/METADATA
a2a_agent_mcpserver_generator-0.1.2.dist-info/WHEEL
a2a_agent_mcpserver_generator-0.1.2.dist-info/entry_points.txt
a2a_agent_mcpserver_generator-0.1.2.dist-info/RECORD
