Metadata-Version: 2.4
Name: a2a-agent-mcpserver-generator
Version: 0.1.2
Summary: Add your description here
Author-email: vincent-pli <justdoit.pli@gmail.com>
Requires-Python: >=3.13
Requires-Dist: a2a-sdk
Requires-Dist: asyncclick>=8.1.8
Requires-Dist: mcp[cli]>=1.8.0
Requires-Dist: pydantic>=2.11.4
Requires-Dist: python-dotenv>=1.1.0
